Identifai/Identifai.py
Identifai/__init__.py
Identifai-0.1.3.dist-info/DESCRIPTION.rst
Identifai-0.1.3.dist-info/METADATA
Identifai-0.1.3.dist-info/RECORD
Identifai-0.1.3.dist-info/WHEEL
Identifai-0.1.3.dist-info/metadata.json
Identifai-0.1.3.dist-info/top_level.txt
