Metadata-Version: 2.0
Name: Identifai
Version: 0.1.3
Summary: Python package for Identifai API
Home-page: https://github.com/KirillKiyko/Identifai
Author: Kirill Kiyko
Author-email: kijko97@gmail.com
License: MIT license
Keywords: Identifai
Platform: UNKNOWN
Classifier: Development Status :: 2 - Pre-Alpha
Classifier: Intended Audience :: Developers
Classifier: License :: OSI Approved :: MIT License
Classifier: Natural Language :: English
Classifier: Programming Language :: Python :: 2
Classifier: Programming Language :: Python :: 2.6
Classifier: Programming Language :: Python :: 2.7
Classifier: Programming Language :: Python :: 3
Classifier: Programming Language :: Python :: 3.3
Classifier: Programming Language :: Python :: 3.4
Classifier: Programming Language :: Python :: 3.5
Requires-Dist: requests
